sclkme/__init__.py
sclkme/io/__init__.py
sclkme/io/read.py
sclkme/tools/__init__.py
sclkme/tools/_kme.py
sclkme/tools/_sketch.py
sclkme/tools/_utils.py
sclkme/utils/__init__.py
sclkme/utils/_joboutput.py
sclkme/utils/_workers.py
sclkme-0.9.4.dist-info/LICENSE
sclkme-0.9.4.dist-info/METADATA
sclkme-0.9.4.dist-info/WHEEL
sclkme-0.9.4.dist-info/RECORD
