Metadata-Version: 2.1
Name: sclkme
Version: 0.9.4
Summary: A Landmark-based Approach for Generating Multi-cellular Sample Embeddings from Single-cell Data
License: MIT
Author: haidyi
Author-email: haidyi@cs.unc.edu
Requires-Python: >=3.8,<3.12
Classifier: License :: OSI Approved :: MIT License
Classifier: Programming Language :: Python :: 3
Classifier: Programming Language :: Python :: 3.8
Classifier: Programming Language :: Python :: 3.9
Classifier: Programming Language :: Python :: 3.10
Classifier: Programming Language :: Python :: 3.11
Requires-Dist: geosketch (>=1.2,<2.0)
Requires-Dist: numpy (>=1.20,<1.24)
Requires-Dist: pandas (>=1.4.4,<2.0.0)
Requires-Dist: pycytodata (==0.1.1)
Requires-Dist: readfcs (>=1.1.7,<2.0.0)
Requires-Dist: rich (>=13.6.0,<14.0.0)
Requires-Dist: scanpy (==1.9.3)
